pyxstar/__init__.py
pyxstar/__main__.py
pyxstar/api.py
pyxstar/main.py
pyxstar-0.2.4.dist-info/LICENSE
pyxstar-0.2.4.dist-info/METADATA
pyxstar-0.2.4.dist-info/WHEEL
pyxstar-0.2.4.dist-info/entry_points.txt
pyxstar-0.2.4.dist-info/RECORD
