Metadata-Version: 2.1
Name: pyxstar
Version: 0.2.4
Summary: A library and commandline tool for managing Pix-Star digital photo frames
Home-page: https://github.com/pgriess/pyxstar
License: MIT
Keywords: pix-star,pixstar
Author: Peter Griess
Author-email: pg@std.in
Requires-Python: >=3.10,<4.0
Classifier: License :: OSI Approved :: MIT License
Classifier: Programming Language :: Python :: 3
Classifier: Programming Language :: Python :: 3.10
Classifier: Programming Language :: Python :: 3.11
Classifier: Programming Language :: Python :: 3.12
Requires-Dist: certifi (>=2024.8.30,<2025.0.0)
Requires-Dist: lxml (>=4.5.0,<5.0.0)
Project-URL: Repository, https://github.com/pgriess/pyxstar
